gnuhealth_control/__init__.py
gnuhealth_control/ghcontrol.py
gnuhealth_control-5.0.2.dist-info/METADATA
gnuhealth_control-5.0.2.dist-info/WHEEL
gnuhealth_control-5.0.2.dist-info/entry_points.txt
gnuhealth_control-5.0.2.dist-info/RECORD
