Metadata-Version: 2.4
Name: gnuhealth-control
Version: 5.0.2
Summary: GNU Health HIS installer and instance administration tool
License-Expression: GPL-3.0-or-later
Keywords: health,hospital,HIS,eHealth,gnuhealth
Author: GNU Solidario
Author-email: health@gnusolidario.org
Maintainer: Luis Falcon
Maintainer-email: falcon@gnuhealth.org
Requires-Python: >=3.10,<3.15
Classifier: Development Status :: 5 - Production/Stable
Classifier: Environment :: Console :: Curses
Classifier: Intended Audience :: Healthcare Industry
Classifier: Intended Audience :: System Administrators
Classifier: Natural Language :: English
Classifier: Operating System :: OS Independent
Classifier: Programming Language :: Python :: 3
Classifier: Programming Language :: Python :: 3.10
Classifier: Programming Language :: Python :: 3.11
Classifier: Programming Language :: Python :: 3.12
Classifier: Programming Language :: Python :: 3.13
Classifier: Programming Language :: Python :: 3.14
Classifier: Topic :: Scientific/Engineering :: Bio-Informatics
Classifier: Topic :: Scientific/Engineering :: Medical Science Apps.
Requires-Dist: proteus (>=7.0.0,<7.1)
Requires-Dist: psutil (>=7.0.0,<8.0.0)
Project-URL: Bug Tracker, https://codeberg.org/gnuhealth/his-utils/issues
Project-URL: Documentation, https://docs.gnuhealth.org
Project-URL: Homepage, https://www.gnuhealth.org
Project-URL: Repository, https://codeberg.org/gnuhealth/his-utils
